pygoodtools/__init__.py
pygoodtools/metaclasses.py
pygoodtools/arm/__init__.py
pygoodtools/arm/functions/__init__.py
pygoodtools/arm/functions/arm_cache.py
pygoodtools/arm/functions/arm_retry.py
pygoodtools/arm/functions/arm_type_checked.py
pygoodtools/arm/map/ArmHashMap.py
pygoodtools/arm/map/ArmMap.py
pygoodtools/arm/map/ArmTreeNode.py
pygoodtools/arm/map/ArmUniqueMap.py
pygoodtools/arm/map/ArmUnorderedMap.py
pygoodtools/arm/map/__init__.py
pygoodtools/arm/objects/ArmCallback.py
pygoodtools/arm/objects/ArmPointer.py
pygoodtools/arm/objects/ArmSignal.py
pygoodtools/arm/objects/ArmSmartPointer.py
pygoodtools/arm/objects/ArmTimeitPtr.py
pygoodtools/arm/objects/ArmTimer.py
pygoodtools/arm/objects/__init__.py
pygoodtools/gtllt/__init__.py
pygoodtools/gtllt/command.py
pygoodtools/gtllt/factory.py
pygoodtools/gtllt/functor.py
pygoodtools/gtllt/mediator.py
pygoodtools/gtllt/meta.py
pygoodtools/gtllt/observer.py
pygoodtools/gtllt/singleton.py
pygoodtools/gtllt/smart_ptr.py
pygoodtools/gtllt/time_ptr.py
pygoodtools/gtllt/visitor.py
pygoodtools/gtllt/gthlt/__init__.py
pygoodtools/gtllt/gthlt/cache.py
pygoodtools/gtllt/gthlt/class_method_checked.py
pygoodtools/gtllt/gthlt/context_manager.py
pygoodtools/gtllt/gthlt/log_calls.py
pygoodtools/gtllt/gthlt/memoization.py
pygoodtools/gtllt/gthlt/retry.py
pygoodtools/gtllt/gthlt/singleton.py
pygoodtools/gtllt/gthlt/timeit.py
pygoodtools/gtllt/gthlt/type_checked.py
pygoodtools/gtmaps/HashMap.py
pygoodtools/gtmaps/Map.py
pygoodtools/gtmaps/TreeMap.py
pygoodtools/gtmaps/UniqueMap.py
pygoodtools/gtmaps/UnorderedMap.py
pygoodtools/gtmaps/__init__.py
pygoodtools/gtsignals/Signal.py
pygoodtools/gtsignals/__init__.py
pygoodtools/gttime/Timer.py
pygoodtools/gttime/__init__.py
pygoodtools/gttypes/Const.py
pygoodtools/gttypes/__init__.py
pygoodtools/gttypes/baseTypes.py
tests/__init__.py
tests/arm/ArmPointer.py
tests/arm/__init__.py
tests/arm/arm_pointer_test.py
tests/gttime/ArmTimer.py
tests/gttime/Timer.py
tests/gttime/__init__.py
pygoodtools-0.5.0.dist-info/LICENSE
pygoodtools-0.5.0.dist-info/METADATA
pygoodtools-0.5.0.dist-info/WHEEL
pygoodtools-0.5.0.dist-info/top_level.txt
pygoodtools-0.5.0.dist-info/RECORD
