Metadata-Version: 2.1
Name: pygoodtools
Version: 0.5.0
Summary: This script sets up the "goodtools" package using setuptools.
Home-page: https://github.com/massonskyi/goodtools
Author: Massonskyi
Author-email: massonskyi@icloud.ru
Classifier: Programming Language :: Python :: 3
Classifier: License :: OSI Approved :: MIT License
Classifier: Operating System :: OS Independent
Requires-Python: >=3.9
License-File: LICENSE
